syftcli/__init__.py
syftcli/cli.py
syftcli/version.py
syftcli/bundle/__init__.py
syftcli/bundle/create.py
syftcli/core/__init__.py
syftcli/core/console.py
syftcli/core/container_engine.py
syftcli/core/proc.py
syftcli/core/register.py
syftcli/core/syft_repo.py
syftcli/core/syft_version.py
syftcli-0.1.11.dist-info/METADATA
syftcli-0.1.11.dist-info/WHEEL
syftcli-0.1.11.dist-info/entry_points.txt
syftcli-0.1.11.dist-info/top_level.txt
syftcli-0.1.11.dist-info/RECORD
