Metadata-Version: 2.1
Name: syftcli
Version: 0.1.11
Summary: Command line utility for Syft
Author: OpenMined <info@openmined.org>
Requires-Dist: requests ==2.31.0
Requires-Dist: pyyaml ==6.0.1
Requires-Dist: packaging ==21.3
Requires-Dist: typer[all] ==0.9.0
Requires-Dist: typing-extensions ==4.6.3
Provides-Extra: build
Requires-Dist: pyinstaller ==5.13.0 ; extra == 'build'
Provides-Extra: dev
Requires-Dist: pytest ; extra == 'dev'
Requires-Dist: pyinstaller ==5.13.0 ; extra == 'dev'
